pikoder/__init__.py
pikoder/ppm_encoder.py
pikoder_ppm_encoder-0.0.2.dist-info/LICENSE
pikoder_ppm_encoder-0.0.2.dist-info/METADATA
pikoder_ppm_encoder-0.0.2.dist-info/WHEEL
pikoder_ppm_encoder-0.0.2.dist-info/top_level.txt
pikoder_ppm_encoder-0.0.2.dist-info/RECORD
