Metadata-Version: 2.1
Name: pikoder-ppm-encoder
Version: 0.0.2
Summary: Small library to use the pikoder ppm encoder
Home-page: https://github.com/vw-wob-it-edu-ngitl/pikoder_ppm_encoder
Author: Torsten Wylegala
Author-email: mail@twyleg.de
License: GPL 3.0
Keywords: pikoder ppm encoder
Platform: UNKNOWN
License-File: LICENSE
